README.md
setup.py
dogebuild_c/__init__.py
dogebuild_c/c_plugin.py
dogebuild_c/gcc_wrapper.py
dogebuild_c/loader.py
dogebuild_c/tasks.py
dogebuild_c.egg-info/PKG-INFO
dogebuild_c.egg-info/SOURCES.txt
dogebuild_c.egg-info/dependency_links.txt
dogebuild_c.egg-info/requires.txt
dogebuild_c.egg-info/top_level.txt