Metadata-Version: 2.1
Name: dogebuild-c
Version: 0.1.0.post1
Summary: C language dogebuild plugin
Home-page: https://github.com/dogebuild/dogebuild-c
Author: Kirill Sulim
Author-email: kirillsulim@gmail.com
License: MIT
Keywords: dogebuild builder
Platform: UNKNOWN
Classifier: Development Status :: 2 - Pre-Alpha
Classifier: Environment :: Console
Classifier: Intended Audience :: Developers
Classifier: License :: OSI Approved :: MIT License
Classifier: Natural Language :: English
Classifier: Operating System :: OS Independent
Classifier: Topic :: Software Development
